ipc_framework/__init__.py
ipc_framework/client.py
ipc_framework/core.py
ipc_framework/demo.py
ipc_framework/exceptions.py
ipc_framework/py.typed
ipc_framework/server.py
ipc_framework/examples/__init__.py
ipc_framework/examples/basic_server.py
ipc_framework/examples/chat_client.py
ipc_framework/examples/file_client.py
ipc_framework/examples/monitoring_client.py
ipc_framework-1.1.2.dist-info/licenses/LICENSE
ipc_framework-1.1.2.dist-info/METADATA
ipc_framework-1.1.2.dist-info/WHEEL
ipc_framework-1.1.2.dist-info/entry_points.txt
ipc_framework-1.1.2.dist-info/top_level.txt
ipc_framework-1.1.2.dist-info/RECORD
