Metadata-Version: 2.4
Name: ipc-framework
Version: 1.1.2
Summary: Python IPC server for high-performance communication with Node.js applications using TCP sockets
Home-page: https://github.com/ifesol/ipc-framework
Author: IPC Framework Team
Author-email: IPC Framework Team <ifesol@example.com>
Maintainer-email: IPC Framework Team <ifesol@example.com>
License: MIT
Project-URL: Homepage, https://github.com/ifesol/ipc-framework
Project-URL: Documentation, https://github.com/ifesol/ipc-framework#readme
Project-URL: Repository, https://github.com/ifesol/ipc-framework.git
Project-URL: Bug Tracker, https://github.com/ifesol/ipc-framework/issues
Keywords: ipc,inter-process-communication,tcp,sockets,nodejs,python,server,microservices,real-time,messaging
Classifier: Development Status :: 4 - Beta
Classifier: Intended Audience :: Developers
Classifier: Topic :: Software Development :: Libraries :: Python Modules
Classifier: Topic :: System :: Networking
Classifier: License :: OSI Approved :: MIT License
Classifier: Programming Language :: Python :: 3
Classifier: Programming Language :: Python :: 3.7
Classifier: Programming Language :: Python :: 3.8
Classifier: Programming Language :: Python :: 3.9
Classifier: Programming Language :: Python :: 3.10
Classifier: Programming Language :: Python :: 3.11
Classifier: Programming Language :: Python :: 3.12
Classifier: Operating System :: OS Independent
Requires-Python: >=3.7
License-File: LICENSE
Provides-Extra: examples
Requires-Dist: psutil>=5.8.0; extra == "examples"
Provides-Extra: dev
Requires-Dist: pytest>=6.0.0; extra == "dev"
Requires-Dist: black>=21.0.0; extra == "dev"
Requires-Dist: flake8>=3.8.0; extra == "dev"
Requires-Dist: mypy>=0.910; extra == "dev"
Requires-Dist: isort>=5.0.0; extra == "dev"
Provides-Extra: all
Requires-Dist: ipc-framework[dev,examples]; extra == "all"
Dynamic: author
Dynamic: home-page
Dynamic: license-file
Dynamic: requires-python
